MANIFEST.in
README.developer.md
README.md
README.setup.md
setup.cfg
setup.py
Karlsruher.egg-info/PKG-INFO
Karlsruher.egg-info/SOURCES.txt
Karlsruher.egg-info/dependency_links.txt
Karlsruher.egg-info/entry_points.txt
Karlsruher.egg-info/requires.txt
Karlsruher.egg-info/top_level.txt
Karlsruher.egg-info/zip-safe
example/auth.yaml.example
karlsruher/__init__.py
karlsruher/__main__.py
karlsruher/__version__.py
karlsruher/brain.py
karlsruher/karlsruher.py
karlsruher/tweepyx.py
tests/__init__.py
tests/brain_test.py
tests/karlsruher_test.py
tests/tweepyx_test.py