Metadata-Version: 2.1
Name: Karlsruher
Version: 3.0b2
Summary: Karlsruher Twitter Robot
Home-page: https://github.com/schlind/Karlsruher
Author: Karlsruher Twitter Robot Society
Author-email: karlsruher-dev@schlind.org
Maintainer: Sascha Schlindwein
Maintainer-email: karlsruher-dev@schlind.org
License: UNKNOWN
Project-URL: Source, https://github.com/schlind/Karlsruher/
Keywords: twitter robot bot retweet cronjob
Platform: UNKNOWN
Classifier: Development Status :: 4 - Beta
Classifier: Environment :: Console
Classifier: Intended Audience :: Developers
Classifier: Programming Language :: Python :: 3
Classifier: Programming Language :: Python :: 3.4
Classifier: Programming Language :: Python :: 3.5
Classifier: Programming Language :: Python :: 3.7
Classifier: Programming Language :: Python :: 3.8
Classifier: License :: Public Domain
Classifier: Topic :: Artistic Software
Classifier: Topic :: Internet
Classifier: Operating System :: MacOS :: MacOS X
Classifier: Operating System :: POSIX :: Linux
Classifier: Operating System :: Unix
Requires-Python: >=3.4, <4
Provides-Extra: dev
Provides-Extra: test
